odoo8_addon_mass_mailing_event-8.0.1.0.0-py2.7-nspkg.pth
odoo8_addon_mass_mailing_event-8.0.1.0.0.dist-info/top_level.txt
odoo8_addon_mass_mailing_event-8.0.1.0.0.dist-info/WHEEL
odoo8_addon_mass_mailing_event-8.0.1.0.0.dist-info/RECORD
odoo8_addon_mass_mailing_event-8.0.1.0.0.dist-info/metadata.json
odoo8_addon_mass_mailing_event-8.0.1.0.0.dist-info/DESCRIPTION.rst
odoo8_addon_mass_mailing_event-8.0.1.0.0.dist-info/METADATA
odoo8_addon_mass_mailing_event-8.0.1.0.0.dist-info/namespace_packages.txt
odoo_addons/mass_mailing_event/__openerp__.py
odoo_addons/mass_mailing_event/__init__.py
odoo_addons/mass_mailing_event/README.rst
odoo_addons/mass_mailing_event/security/ir.model.access.csv
odoo_addons/mass_mailing_event/models/event_registration.py
odoo_addons/mass_mailing_event/models/res_partner.py
odoo_addons/mass_mailing_event/models/mail_mass_mailing_contact.py
odoo_addons/mass_mailing_event/models/event_registration_state.py
odoo_addons/mass_mailing_event/models/__init__.py
odoo_addons/mass_mailing_event/models/mail_mass_mailing.py
odoo_addons/mass_mailing_event/i18n/es.po
odoo_addons/mass_mailing_event/views/mass_mailing_view.xml
odoo_addons/mass_mailing_event/data/event_state_data.xml
odoo_addons/mass_mailing_event/tests/test_mass_mailing_event.py
odoo_addons/mass_mailing_event/tests/__init__.py
odoo_addons/mass_mailing_event/static/description/icon.png
